[{"s": "khvs-pri-soderzhanii-oi-chto-eto-v-kvitantsii", "t": "Что такое ХВС при содержании ОИ в квитанции ЖКХ", "i": "🔍", "c": "rasshifrovka-kvitantsij"}, {"s": "khvs-na-gvs-chto-eto-v-kvitantsii", "t": "ХВС на ГВС в квитанции: что это и как расшифровать", "i": "🔍", "c": "rasshifrovka-kvitantsij"}, {"s": "kholodnoe-vodosnabzhenie-pk-v-kvitantsii-chto", "t": "Холодное водоснабжение ПК в квитанции: расшифровка и тарифы", "i": "🔍", "c": "rasshifrovka-kvitantsij"}, {"s": "khvs-pk-v-kvitantsii-chto-eto-znachit", "t": "ХВС ПК в квитанции ЖКХ: расшифровка и проверка", "i": "🔍", "c": "rasshifrovka-kvitantsij"}, {"s": "khvs-pk-v-kvitantsii-chto-eto-takoe", "t": "ХВС ПК в квитанции ЖКХ: расшифровка и расчет", "i": "📁", "c": null}, {"s": "khvs-povyshayushchij-koeffitsient-v-kvitantsii-chto-eto-znachit", "t": "Повышающий коэффициент ХВС в квитанции: что это и как убрать", "i": "🏠", "c": "oplata-zhkkh"}, {"s": "kholodnoe-v-s-v-kvitantsii-chto-eto", "t": "Холодное водоснабжение в квитанции ЖКХ: что это и как читать", "i": "🔍", "c": "rasshifrovka-kvitantsij"}, {"s": "khvs-na-gvs-chto-eto-v-kvitantsii-otkuda", "t": "Расшифровка ХВС на ГВС в квитанции: откуда берется и как считать", "i": "🔍", "c": "rasshifrovka-kvitantsij"}, {"s": "kholodnoe-vodosnabzhenie-v-kvitantsii-kak-proverit-raschet", "t": "Холодное водоснабжение в квитанции: как проверить расчет", "i": "🔍", "c": "rasshifrovka-kvitantsij"}, {"s": "khvs-kpu-chto-eto-takoe-v-zhkkh", "t": "ХВС и КПУ в квитанциях ЖКХ: расшифровка и расчет", "i": "🔍", "c": "rasshifrovka-kvitantsij"}, {"s": "khvs-koeffitsient-v-kvitantsii-chto-eto", "t": "ХВС в квитанции ЖКХ: что это такое и как проверить", "i": "🔍", "c": "rasshifrovka-kvitantsij"}, {"s": "kholodnaya-voda-soid-chto-eto-v-kvitantsii", "t": "Холодная вода СОИД в квитанции: расшифровка и расчет", "i": "🔍", "c": "rasshifrovka-kvitantsij"}, {"s": "khvs-pd-chto-eto-v-kvitantsii", "t": "ХВС и ПД в квитанции ЖКХ: расшифровка и проверка", "i": "🔍", "c": "rasshifrovka-kvitantsij"}, {"s": "khgvs-chto-takoe-zhkkh", "t": "Расшифровка ХГВС в квитанции ЖКХ: что это и как платить", "i": "🔍", "c": "rasshifrovka-kvitantsij"}, {"s": "khvs-chto-eto-takoe-v-zhkkh-rasshifrovka", "t": "ХВС в квитанции ЖКХ: расшифровка, нормативы и расчет", "i": "🔍", "c": "rasshifrovka-kvitantsij"}, {"s": "kholodnaya-i-goryachaya-voda-kak-oboznachaetsya-v-kvitantsii", "t": "Холодная и горячая вода в квитанции: расшифровка и аббревиатуры", "i": "🔍", "c": "rasshifrovka-kvitantsij"}, {"s": "kholodnoe-vodosnabzhenie-pitevaya-voda-chto-eto-v-kvitantsii", "t": "Что такое ХВС в квитанции ЖКХ: расшифровка и расчет", "i": "🔍", "c": "rasshifrovka-kvitantsij"}, {"s": "khvs-v-platezhke-chto-eto-znachit", "t": "ХВС в платёжке: расшифровка и проверка начислений", "i": "🔍", "c": "rasshifrovka-kvitantsij"}, {"s": "kholodnaya-voda-dlya-goryachej-vody-chto-eto-v-kvitantsii", "t": "Холодная вода для ГВС в квитанции: расшифровка и расчет", "i": "🔍", "c": "rasshifrovka-kvitantsij"}, {"s": "khvs-chto-eto-takoe-v-zhkkh", "t": "ХВС в ЖКХ: что это такое, расшифровка, нормативы и цены", "i": "🔍", "c": "rasshifrovka-kvitantsij"}, {"s": "kholodnoe-vodosnabzhenie-v-kvitantsii-chto-eto-rb", "t": "Холодное водоснабжение в квитанции: что это в РБ", "i": "🔍", "c": "rasshifrovka-kvitantsij"}, {"s": "kholodnoe-vodootvedenie-chto-eto-takoe-v-kvitantsii", "t": "Холодное водоотведение в квитанции: что это и как проверить", "i": "🔍", "c": "rasshifrovka-kvitantsij"}, {"s": "kholodnoe-vodosnabzhenie-odn-chto-eto-takoe-v-kvitantsii", "t": "Холодное водоснабжение ОДН в квитанции: расшифровка и расчет", "i": "🔍", "c": "rasshifrovka-kvitantsij"}, {"s": "khvs-chto-eto-v-zhkkh", "t": "ХВС в квитанции ЖКХ: расшифровка и расчёт", "i": "🔍", "c": "rasshifrovka-kvitantsij"}, {"s": "kholodnoe-vodosnabzhenie-odn-v-kvitantsii-chto-eto", "t": "Холодное водоснабжение ОДН в квитанции: что это и как проверить", "i": "🔍", "c": "rasshifrovka-kvitantsij"}, {"s": "khvs-dlya-gvs-v-kvitantsii-chto-oznachaet", "t": "ХВС для ГВС в квитанции: что означает и как проверить", "i": "🔍", "c": "rasshifrovka-kvitantsij"}, {"s": "khvs-odn-v-kvitantsii-chto-eto-znachit", "t": "ХВС ОДН в квитанции: что значит, как рассчитать и проверить", "i": "🔍", "c": "rasshifrovka-kvitantsij"}, {"s": "khoum-kredit-bank-kak-oplatit-zhkkh", "t": "Как оплатить ЖКХ через Хоум Кредит Банк: приложения и банкоматы", "i": "🏠", "c": "oplata-zhkkh"}, {"s": "khvs-bojler-v-kvitantsii-chto-eto", "t": "ХВС бойлер в квитанции: расшифровка и проверка", "i": "🔍", "c": "rasshifrovka-kvitantsij"}, {"s": "khoum-kredit-kak-poluchit-kvitantsiyu-ob-oplate", "t": "Как получить квитанцию об оплате Хоум Кредит: 5 способов", "i": "🏦", "c": "bankovskie-operatsii"}, {"s": "khol-vodosnabzhenie-v-kvitantsii-chto-eto", "t": "ХОЛ в квитанции: расшифровка и что это такое", "i": "🔍", "c": "rasshifrovka-kvitantsij"}, {"s": "khvs-povyshennyj-koeffitsient-chto-eto-v-platezhke", "t": "ХВС повышенный коэффициент: причины и что делать", "i": "🔍", "c": "rasshifrovka-kvitantsij"}, {"s": "khvs-pri-soi-chto-eto-v-kvitantsii", "t": "ХВС при СОИ: расшифровка, причины и как проверить", "i": "🔍", "c": "rasshifrovka-kvitantsij"}, {"s": "kholodnaya-voda-ipu-chto-v-kvitantsii", "t": "Холодная вода в квитанции ЖКХ: расшифровка и нормы", "i": "🔍", "c": "rasshifrovka-kvitantsij"}, {"s": "khvs-v-kvitantsii-za-vodu-chto-eto", "t": "ХВС в квитанции за воду: что это такое и как рассчитать", "i": "🔍", "c": "rasshifrovka-kvitantsij"}, {"s": "khvs-ipu-chto-eto-v-kvitantsii", "t": "ХВС и ИПУ в квитанции ЖКХ: расшифровка и значение", "i": "🔍", "c": "rasshifrovka-kvitantsij"}, {"s": "khv-dlya-podogreva-v-kvitantsii-chto-eto", "t": "ХВ для подогрева в квитанции: что это и как проверить начисление", "i": "🔍", "c": "rasshifrovka-kvitantsij"}, {"s": "khvs-kpu-chto-eto-v-kvitantsii-rasshifrovka", "t": "ХВС и КПУ в квитанции: расшифровка и проверка показаний", "i": "🔍", "c": "rasshifrovka-kvitantsij"}, {"s": "khusnullizatsiya-v-dejstvii-kak-na-samom-dele-rabotaet-finansovaya-piramida-zhkkh", "t": "Хуснуллизация ЖКХ: схема работы и риски для собственников", "i": "🏢", "c": "upravlyayushchie-kompanii"}, {"s": "khvs-dlya-gvs-chto-eto-takoe-v-zhkkh", "t": "ХВС для ГВС в квитанции ЖКХ: что это и как проверить начисления", "i": "🔍", "c": "rasshifrovka-kvitantsij"}, {"s": "khvs-povyshayushchij-koeffitsient-chto-eto-takoe-v-kvitantsii", "t": "Повышающий коэффициент ХВС в квитанции: что это и как проверить", "i": "🔍", "c": "rasshifrovka-kvitantsij"}, {"s": "khvs-soi-v-kvitantsii-za-kvartiru-chto-eto", "t": "ХВС СОИ в квитанции: расшифровка и расчет", "i": "🔍", "c": "rasshifrovka-kvitantsij"}, {"s": "kholodnoe-v-s-odn-chto-eto-v-kvitantsii", "t": "Холодное водоснабжение в квитанции ЖКХ: расшифровка и расчет", "i": "🔍", "c": "rasshifrovka-kvitantsij"}, {"s": "khv-na-soi-v-kvitantsii-chto", "t": "Аббревиатура ХВ в квитанции: расшифровка и расчет", "i": "🔍", "c": "rasshifrovka-kvitantsij"}, {"s": "khvs-v-kvitantsii-za-kvartiru-chto-eto-znachit", "t": "ХВС в квитанции ЖКХ: расшифровка и проверка тарифов", "i": "🔍", "c": "rasshifrovka-kvitantsij"}, {"s": "kholodnaya-voda-stok-chto-eto-v-kvitantsii-zhkkh", "t": "Холодная вода сток в квитанции: расшифровка и расчет", "i": "🔍", "c": "rasshifrovka-kvitantsij"}, {"s": "khvs-kpu-rasshifrovka-v-kvitantsii-chto-eto-takoe", "t": "Расшифровка ХВС и КПУ в квитанции ЖКХ: что это значит", "i": "🔍", "c": "rasshifrovka-kvitantsij"}, {"s": "kholodnoe-vodosnabzhenie-v-kvitantsii-chto-eto", "t": "Холодное водоснабжение в квитанции: как читать и проверять", "i": "🔍", "c": "rasshifrovka-kvitantsij"}, {"s": "khvs-v-kvitantsii-za-kvartiru-chto-takoe", "t": "ХВС в квитанции ЖКХ: что значит и как проверить расчет", "i": "🔍", "c": "rasshifrovka-kvitantsij"}, {"s": "kholodnoe-vodosnabzhenie-pk-v-kvitantsii-chto-eto-takoe", "t": "Холодное водоснабжение в квитанции: расшифровка и нормы", "i": "🔍", "c": "rasshifrovka-kvitantsij"}, {"s": "kholodnoe-vodosnabzhenie-vk-v-kvitantsii-chto-takoe", "t": "Холодное водоснабжение в квитанции: что это и как проверить", "i": "🔍", "c": "rasshifrovka-kvitantsij"}, {"s": "kholodnaya-voda-dlya-gvs-v-kvitantsii-chto-znachit", "t": "Холодная вода на ГВС в квитанции: что это и как считать", "i": "🔍", "c": "rasshifrovka-kvitantsij"}, {"s": "khudozhestvennyj-konkurs-moya-ulitsa-i-dom-chto-takoe-zhkkh", "t": "Художественный конкурс «Моя улица и дом»: что такое ЖКХ", "i": "🏢", "c": "upravlyayushchie-kompanii"}, {"s": "khvs-dlya-gvs-chto-eto-takoe-v-kvitantsii", "t": "ХВС для ГВС в квитанции: расшифровка и расчет", "i": "🔍", "c": "rasshifrovka-kvitantsij"}, {"s": "khvs-na-odn-v-kvitantsii-chto-eto-takoe", "t": "ХВС на ОДН в квитанции: расшифровка и расчет", "i": "🔍", "c": "rasshifrovka-kvitantsij"}, {"s": "khvs-v-kvitantsii-kak-poschitat", "t": "Аббревиатура ХВС в квитанции: расшифровка и расчет оплаты", "i": "🔍", "c": "rasshifrovka-kvitantsij"}, {"s": "khvs-v-platezhke-chto-eto", "t": "ХВС в платежке: расшифровка аббревиатуры и расчет", "i": "🔍", "c": "rasshifrovka-kvitantsij"}, {"s": "khvs-dlya-nuzhd-gvs-chto-eto-v-kvitantsii", "t": "ХВС для ГВС в квитанции: что это и как проверить расчеты", "i": "🔍", "c": "rasshifrovka-kvitantsij"}, {"s": "khvs-dpu-chto-eto-v-kvitantsii", "t": "ХВС ДПУ в квитанции: расшифровка, расчет и проверка", "i": "🔍", "c": "rasshifrovka-kvitantsij"}, {"s": "khanty-mansijsk-zhkkh-kak-poyavlyaetsya-penii", "t": "Пени за ЖКХ в ХМАО: расчет, сроки и законные способы отмены", "i": "⚖️", "c": "dolgi-i-peni"}, {"s": "khvs-pu1-v-kvitantsii-chto-eto", "t": "ХВС ПУ1 в квитанции: что это, расшифровка и проверка", "i": "🔍", "c": "rasshifrovka-kvitantsij"}, {"s": "kholodnoe-vs-odn-v-kvitantsii-chto-eto", "t": "Холодное ВС ОДН в квитанции: что это и как проверить", "i": "🔍", "c": "rasshifrovka-kvitantsij"}, {"s": "khvs-na-soi-chto-eto-znachit-v-kvitantsii", "t": "ХВС на сои: что это значит в квитанции ЖКХ", "i": "🔍", "c": "rasshifrovka-kvitantsij"}, {"s": "khv-snabzhenie-v-kvitantsii-chto", "t": "Аббревиатура ХВ в квитанции ЖКХ: расшифровка и расчет", "i": "🔍", "c": "rasshifrovka-kvitantsij"}, {"s": "kholodnaya-voda-dlya-goryachej-v-kvitantsii-chto", "t": "Холодная вода для горячей в квитанции: причины и что делать", "i": "🔍", "c": "rasshifrovka-kvitantsij"}, {"s": "khv-dlya-gvs-v-kvitantsii-chto", "t": "ХВС для ГВС в квитанции: что это и как проверить расчет", "i": "🔍", "c": "rasshifrovka-kvitantsij"}, {"s": "khoum-kredit-kak-platit-zhkkh", "t": "Как оплатить ЖКХ через Хоум Кредит Банк: инструкции", "i": "🏠", "c": "oplata-zhkkh"}, {"s": "khvs-na-nuzhdy-gvs-chto-eto-v-kvitantsii", "t": "ХВС на нужды ГВС в квитанции: что это и зачем платить", "i": "🔍", "c": "rasshifrovka-kvitantsij"}, {"s": "khvs-v-kvitantsii-chto-eto-oboznachaet", "t": "ХВС в квитанции ЖКХ: расшифровка и расчет стоимости", "i": "🔍", "c": "rasshifrovka-kvitantsij"}, {"s": "khvs-eto-v-kvitantsii-chto", "t": "ХВС в квитанции: расшифровка, тарифы и расчет оплаты", "i": "🔍", "c": "rasshifrovka-kvitantsij"}, {"s": "khvs-kpu-rasshifrovka-v-kvitantsii-chto-eto-znachit", "t": "ХВС и КПУ в квитанции: расшифровка и проверка", "i": "🔍", "c": "rasshifrovka-kvitantsij"}, {"s": "kholodnaya-voda-na-podogrev-v-kvitantsii-chto", "t": "Холодная вода на подогрев в квитанции: расшифровка строки", "i": "🔍", "c": "rasshifrovka-kvitantsij"}, {"s": "kholodnaya-voda-kpov-chto-eto-v-kvitantsii", "t": "Холодная вода ХВС в квитанции ЖКХ: расшифровка и нормы", "i": "🔍", "c": "rasshifrovka-kvitantsij"}, {"s": "khoz-raskhody-kakoj-kod-v-platezhke", "t": "Хоз расходы: какой код ставить в платежном поручении", "i": "💰", "c": "nalogi-i-poshliny"}, {"s": "khv-na-soi-v-kvitantsii-chto-eto-takoe", "t": "ХВ на сои в квитанции ЖКХ: расшифровка и проверка", "i": "🔍", "c": "rasshifrovka-kvitantsij"}, {"s": "khvs-soi-chto-eto-znachit-zhkkh", "t": "ХВС в квитанции ЖКХ: что значит и как проверить расчет", "i": "🔍", "c": "rasshifrovka-kvitantsij"}, {"s": "khvs-gvs-ipu-chto-eto-v-kvitantsii", "t": "ХВС, ГВС и ИПУ в квитанции ЖКХ: расшифровка и расчет", "i": "🔍", "c": "rasshifrovka-kvitantsij"}, {"s": "kholodnaya-voda-na-odn-chto-eto-takoe-v-kvitantsii", "t": "Холодная вода на ОДН в квитанции: что это значит", "i": "🔍", "c": "rasshifrovka-kvitantsij"}, {"s": "khvs-na-gvs-v-kvitantsii-chto-pisat", "t": "ХВС на ГВС в квитанции: что писать и как исправить", "i": "🔍", "c": "rasshifrovka-kvitantsij"}, {"s": "khol-vodosnabzhenie-v-kvitantsii-chto-eto-takoe", "t": "Хол в квитанции ЖКХ: что это и как проверить расчет", "i": "🔍", "c": "rasshifrovka-kvitantsij"}, {"s": "khvs-pk-v-kvitantsii-chto-eto", "t": "ХВС ПК в квитанции ЖКХ: расшифровка и проверка", "i": "🔍", "c": "rasshifrovka-kvitantsij"}, {"s": "khv-v-kvitantsii-chto-eto", "t": "ХВ в квитанции ЖКХ: что это такое и как проверить", "i": "🔍", "c": "rasshifrovka-kvitantsij"}, {"s": "khvs-dlya-gvs-v-kvitantsii-za-kvartiru-chto-eto", "t": "ХВС для ГВС в квитанции: расшифровка и расчет", "i": "🔍", "c": "rasshifrovka-kvitantsij"}, {"s": "khvs-povyshayushchij-koeffitsient-v-kvitantsii-chto-eto", "t": "Повышающий коэффициент в квитанции: что это и как убрать", "i": "🔍", "c": "rasshifrovka-kvitantsij"}, {"s": "khvs-v-kvitantsii-za-kvartiru-chto-eto", "t": "ХВС в квитанции ЖКУ: расшифровка, расчет и проверка", "i": "🔍", "c": "rasshifrovka-kvitantsij"}, {"s": "khvs-pu-odn-v-kvitantsii-chto", "t": "ХВС и ПУ ОДН в квитанции: что это и как проверить", "i": "🔍", "c": "rasshifrovka-kvitantsij"}, {"s": "kholodnaya-voda-v-kvitantsii-chto-eto", "t": "Холодная вода в квитанции: как читать и проверять", "i": "🔍", "c": "rasshifrovka-kvitantsij"}, {"s": "khochu-otkryt-upravlyayushchuyu-kompaniyu-zhkkh-s-chego-nachat", "t": "Как открыть управляющую компанию ЖКХ: пошаговая инструкция", "i": "🏢", "c": "upravlyayushchie-kompanii"}, {"s": "khvs-dlya-gvs-v-kvitantsii-za-kvartiru-chto-takoe", "t": "ХВС для ГВС в квитанции: что это и зачем платят", "i": "🔍", "c": "rasshifrovka-kvitantsij"}, {"s": "kholodnoe-vodosnabzhenie-dlya-gvs-v-kvitantsii-chto-eto-takoe", "t": "Что такое холодное водоснабжение для ГВС в квитанции ЖКХ", "i": "🔍", "c": "rasshifrovka-kvitantsij"}, {"s": "khvs-v-kvitantsii-za-vodu-chto-takoe", "t": "ХВС в квитанции: что это и как проверить расчет", "i": "🔍", "c": "rasshifrovka-kvitantsij"}, {"s": "khvs-pov-koef-v-kvitantsii-chto-eto", "t": "ХВС пов. коэф. в квитанции: что это и как проверить", "i": "🔍", "c": "rasshifrovka-kvitantsij"}, {"s": "khov-v-kvitantsii-chto-eto", "t": "ХОВ в квитанции ЖКХ: расшифровка, формула расчета и нормативы", "i": "🔍", "c": "rasshifrovka-kvitantsij"}, {"s": "kholodnaya-voda-teplonositel-chto-eto-v-kvitantsii", "t": "Холодная вода теплоноситель в квитанции: что это такое", "i": "🔍", "c": "rasshifrovka-kvitantsij"}, {"s": "khol-v-i-stok-chto-eto-v-kvitantsii", "t": "Хол в и сток в квитанции: расшифровка и значение", "i": "🔍", "c": "rasshifrovka-kvitantsij"}]