[{"s": "pk-v-kvitantsii-chto-eto", "t": "ПК в квитанции ЖКХ: что это такое и законно ли списание", "i": "🔍", "c": "rasshifrovka-kvitantsij"}, {"s": "pk-15-v-kvitantsii-chto-eto-znachit", "t": "ПК 1.5 в квитанции: расшифровка и причины начисления", "i": "🔍", "c": "rasshifrovka-kvitantsij"}, {"s": "pko-kvitantsiya-komu-otdaetsya", "t": "Кому отдается копия ПКО: правила хранения и выдачи", "i": "📁", "c": "drugoe"}, {"s": "pks-chto-eto-takoe-v-zhkkh", "t": "ПКС в квитанции ЖКХ: расшифровка, нормативы и порядок оплаты", "i": "🔍", "c": "rasshifrovka-kvitantsij"}]