[{"s": "tarify-zhkkh-chto-takoe-pk", "t": "Что такое ПК в тарифах ЖКХ: расшифровка и расчет", "i": "🔍", "c": "rasshifrovka-kvitantsij"}, {"s": "tattelekom-oplata-kvitantsii-do-kakogo-chisla", "t": "Оплата Таттелеком: до какого числа вносить платеж", "i": "🏠", "c": "oplata-zhkkh"}, {"s": "tarify-zhkkh-chto-eto", "t": "Тарифы ЖКХ: что это, как считаются и от чего зависят", "i": "🔍", "c": "rasshifrovka-kvitantsij"}, {"s": "tarify-zhkkh-chto-v-nikh-vkhodit", "t": "Тарифы ЖКХ: что входит в квитанцию и как проверить расчет", "i": "🔍", "c": "rasshifrovka-kvitantsij"}, {"s": "tarif-zhkkh-kak-poschitat", "t": "Как рассчитать тариф ЖКХ: формулы, нормативы и примеры", "i": "🔍", "c": "rasshifrovka-kvitantsij"}, {"s": "tarify-zhkkh-chto-novogo", "t": "Тарифы ЖКХ: что нового в правилах расчета и оплате", "i": "🏠", "c": "oplata-zhkkh"}, {"s": "tambov-kuda-zhalovatsya-na-zhkkh", "t": "Жалоба на ЖКХ в Тамбове: куда и как написать", "i": "🏢", "c": "upravlyayushchie-kompanii"}, {"s": "tarify-zhkkh-iz-chego-sostoyat", "t": "Из чего состоит тариф ЖКХ: полная расшифровка", "i": "🔍", "c": "rasshifrovka-kvitantsij"}, {"s": "tarify-upravlyayushchej-kompanii-zhkkh-kak-rasschitat", "t": "Как рассчитать тарифы ЖКХ: формула и порядок действий", "i": "🏢", "c": "upravlyayushchie-kompanii"}, {"s": "tarify-v-gis-zhkkh-gde-posmotret", "t": "Тарифы в ГИС ЖКХ: где найти и как проверить", "i": "🔍", "c": "rasshifrovka-kvitantsij"}, {"s": "tarify-zhkkh-kogda-povyshenie", "t": "Когда повышение тарифов ЖКХ: даты и порядок расчета", "i": "🏠", "c": "oplata-zhkkh"}, {"s": "tarify-na-zhkkh-kto-ustanavlivaet", "t": "Тарифы на ЖКУ: кто их устанавливает и как проверить", "i": "🏠", "c": "oplata-zhkkh"}, {"s": "tarify-na-chto-povysitsya-s-1-dekabrya-zhkkh", "t": "Тарифы ЖКХ с 1 декабря: что изменится и как платить", "i": "🏠", "c": "oplata-zhkkh"}, {"s": "tarify-na-uslugi-zhkkh-ustanavlivayut-kto", "t": "Тарифы на услуги ЖКХ: кто устанавливает и утверждает", "i": "🏠", "c": "oplata-zhkkh"}, {"s": "tarify-zhkkh-s-kakogo-mesyatsa-povysyat", "t": "С какого месяца повысят тарифы ЖКХ в 2026 году", "i": "🏠", "c": "oplata-zhkkh"}, {"s": "tarify-zhkkh-kak-formiruyutsya", "t": "Тарифы ЖКХ: как формируются и от чего зависят цены", "i": "🏠", "c": "oplata-zhkkh"}, {"s": "tarify-na-zhkkh-vyrastut-skolko-budem-platit-za-teplo-i-vodu", "t": "Тарифы ЖКХ: на сколько вырастут и как рассчитать платеж", "i": "🏠", "c": "oplata-zhkkh"}, {"s": "tarify-zhkkh-kto-ustanavlivaet-v-regionakh", "t": "Тарифы ЖКХ: кто устанавливает цены в регионах РФ", "i": "🏠", "c": "oplata-zhkkh"}]